[
    {
        "ParameterKey": "Bucket",
        "ParameterValue": "{{ parameters.bucket }}"
    },
    {
        "ParameterKey": "AvailabilityZone",
        "ParameterValue": "{{ parameters.availability_zone }}"
    },
    {
        "ParameterKey": "BatchInstanceType",
        "ParameterValue": "{{ parameters.batch_instance_type }}"
    },
    {
        "ParameterKey": "BatchJobDefinitionName",
        "ParameterValue": "ReviewModelBatchJobDefinition"
    },
    {
        "ParameterKey": "BatchJobQueueName",
        "ParameterValue": "ReviewModelBatchJobQueue"
    },
    {
        "ParameterKey": "BotInstanceType",
        "ParameterValue": "{{ parameters.bot_instance_type }}"
    },
    {
        "ParameterKey": "BotInstanceAmi",
        "ParameterValue": "{{ parameters.bot_instance_ami }}"
    }
]